docker_volume_easyfuse-0.2.1.data/data/share/easyfuse/systemd/easyfuse.service
docker_volume_easyfuse-0.2.1.data/data/share/easyfuse/systemd/easyfuse.service.dev
docker_volume_easyfuse-0.2.1.data/data/share/easyfuse/systemd/easyfuse.service.venv
docker_volume_easyfuse-0.2.1.data/data/share/easyfuse/systemd/easyfuse.socket
easyfuse/Driver.py
easyfuse/Handler.py
easyfuse/MountDatabase.py
easyfuse/__init__.py
easyfuse/__main__.py
easyfuse/systemd_setup.py
easyfuse/systemd/easyfuse.service
easyfuse/systemd/easyfuse.service.dev
easyfuse/systemd/easyfuse.service.venv
easyfuse/systemd/easyfuse.socket
docker_volume_easyfuse-0.2.1.dist-info/LICENSE
docker_volume_easyfuse-0.2.1.dist-info/METADATA
docker_volume_easyfuse-0.2.1.dist-info/WHEEL
docker_volume_easyfuse-0.2.1.dist-info/top_level.txt
docker_volume_easyfuse-0.2.1.dist-info/RECORD
