Metadata-Version: 2.1
Name: docker-volume-easyfuse
Version: 0.2.1
Summary: simple FUSE volume driver for Docker
Home-page: https://github.com/Marandil/docker-volume-easyfuse
Author: Marcin Słowik
Author-email: me@marandil.pl
License: UNKNOWN
Platform: UNKNOWN
Classifier: Development Status :: 3 - Alpha
Classifier: Framework :: AsyncIO
Classifier: Programming Language :: Python :: 3
Classifier: License :: OSI Approved :: GNU General Public License v3 (GPLv3)
Classifier: Operating System :: POSIX :: Linux
Requires-Python: >=3.6
Requires-Dist: aiohttp
